cubeforge/__init__.py
cubeforge/constants.py
cubeforge/model.py
cubeforge/writers.py
cubeforge-0.2.2.dist-info/licenses/LICENSE
cubeforge-0.2.2.dist-info/METADATA
cubeforge-0.2.2.dist-info/WHEEL
cubeforge-0.2.2.dist-info/top_level.txt
cubeforge-0.2.2.dist-info/RECORD
