Metadata-Version: 2.4
Name: cubeforge
Version: 0.2.2
Summary: Generate 3D (STL) files from cube definitions.
Author-email: Teddy van Jerry <me@teddy-van-jerry.org>
License: MIT License
Project-URL: Homepage, https://github.com/Teddy-van-Jerry/cubeforge
Project-URL: Documentation, https://cubeforge.wqzhao.org
Project-URL: Bug Tracker, https://github.com/Teddy-van-Jerry/cubeforge/issues
Keywords: stl,3d,mesh,voxel,cube,geometry,cad
Classifier: Programming Language :: Python :: 3
Classifier: License :: OSI Approved :: MIT License
Classifier: Operating System :: OS Independent
Classifier: Development Status :: 3 - Alpha
Classifier: Intended Audience :: Developers
Classifier: Intended Audience :: Science/Research
Classifier: Topic :: Multimedia :: Graphics :: 3D Modeling
Classifier: Topic :: Software Development :: Libraries :: Python Modules
Requires-Python: >=3.8
License-File: LICENSE
Dynamic: license-file
